filemason/__init__.py
filemason/cli.py
filemason/exceptions.py
filemason/orchestrator.py
filemason/config/__init__.py
filemason/config/config.toml
filemason/config/config_loader.py
filemason/models/__init__.py
filemason/models/action_plan.py
filemason/models/action_step.py
filemason/models/failed_action.py
filemason/models/file_item.py
filemason/models/run_result.py
filemason/services/__init__.py
filemason/services/classifier.py
filemason/services/executor.py
filemason/services/planner.py
filemason/services/reader.py
filemason-0.1.1.dist-info/licenses/LICENSE
filemason-0.1.1.dist-info/METADATA
filemason-0.1.1.dist-info/WHEEL
filemason-0.1.1.dist-info/entry_points.txt
filemason-0.1.1.dist-info/top_level.txt
filemason-0.1.1.dist-info/RECORD
