Metadata-Version: 2.4
Name: filemason
Version: 0.1.1
Summary: a file organizing cli tool
Author: Karson Bryant
Project-URL: Homepage, https://github.com/KarBryant/FileMason
Project-URL: Source, https://github.com/KarBryant/FileMason
Project-URL: Issues, https://github.com/KarBryant/FileMason/issues
Keywords: filemason,file organizer,cli tool
Requires-Python: >=3.11
License-File: LICENSE
Requires-Dist: typer>=0.20.0
Requires-Dist: rich>=14.2.0
Requires-Dist: pydantic>=2.12.0
Provides-Extra: dev
Requires-Dist: pytest>=8.0.0; extra == "dev"
Requires-Dist: pytest-cov>=4.1; extra == "dev"
Requires-Dist: black>=24.0.0; extra == "dev"
Requires-Dist: ruff>=0.5.0; extra == "dev"
Dynamic: license-file
